
[
  {
    "id": 1,
    "nombre": "Canbo",
    "slug": "canbo",
    "logo": "https://images.unsplash.com/photo-1583337130417-3346a1be7dee?w=200&h=100&fit=crop&crop=center"
  },
  {
    "id": 2,
    "nombre": "Proteggo",
    "slug": "proteggo", 
    "logo": "https://images.unsplash.com/photo-1558618666-fcd25c85cd64?w=200&h=100&fit=crop&crop=center"
  },
  {
    "id": 3,
    "nombre": "Don Fermín",
    "slug": "don-fermin",
    "logo": "https://images.unsplash.com/photo-1548199973-03cce0bbc87b?w=200&h=100&fit=crop&crop=center"
  },
  {
    "id": 4,
    "nombre": "Royal Canin",
    "slug": "royal-canin",
    "logo": "https://images.unsplash.com/photo-1601758228041-f3b2795255f1?w=200&h=100&fit=crop&crop=center"
  },
  {
    "id": 5,
    "nombre": "Hill's",
    "slug": "hills",
    "logo": "https://images.unsplash.com/photo-1583337130417-3346a1be7dee?w=200&h=100&fit=crop&crop=center"
  },
  {
    "id": 6,
    "nombre": "Pro Plan",
    "slug": "pro-plan",
    "logo": "https://images.unsplash.com/photo-1558618666-fcd25c85cd64?w=200&h=100&fit=crop&crop=center"
  },
  {
    "id": 7,
    "nombre": "Pedigree",
    "slug": "pedigree",
    "logo": "https://images.unsplash.com/photo-1548199973-03cce0bbc87b?w=200&h=100&fit=crop&crop=center"
  },
  {
    "id": 8,
    "nombre": "Whiskas",
    "slug": "whiskas",
    "logo": "https://images.unsplash.com/photo-1601758228041-f3b2795255f1?w=200&h=100&fit=crop&crop=center"
  }
]
